wizit_context_ingestor/.DS_Store
wizit_context_ingestor/__init__.py
wizit_context_ingestor/application/__init__.py
wizit_context_ingestor/application/context_chunk_service.py
wizit_context_ingestor/application/interfaces.py
wizit_context_ingestor/application/kdb_service.py
wizit_context_ingestor/application/transcription_service.py
wizit_context_ingestor/data/__init__.py
wizit_context_ingestor/data/kdb.py
wizit_context_ingestor/data/prompts.py
wizit_context_ingestor/data/storage.py
wizit_context_ingestor/domain/__init__.py
wizit_context_ingestor/domain/models.py
wizit_context_ingestor/domain/services.py
wizit_context_ingestor/infra/__init__.py
wizit_context_ingestor/infra/aws_model.py
wizit_context_ingestor/infra/persistence/__init__.py
wizit_context_ingestor/infra/persistence/local_storage.py
wizit_context_ingestor/infra/persistence/s3_storage.py
wizit_context_ingestor/infra/rag/chroma_embeddings.py
wizit_context_ingestor/infra/rag/pg_embeddings.py
wizit_context_ingestor/infra/rag/redis_embeddings.py
wizit_context_ingestor/infra/rag/semantic_chunks.py
wizit_context_ingestor/infra/secrets/__init__.py
wizit_context_ingestor/infra/secrets/aws_secrets_manager.py
wizit_context_ingestor/infra/vertex_model.py
wizit_context_ingestor/main.py
wizit_context_ingestor/main_chunks.py
wizit_context_ingestor/services/.DS_Store
wizit_context_ingestor/services/__init__.py
wizit_context_ingestor/services/chunks.py
wizit_context_ingestor/services/parse_doc.py
wizit_context_ingestor/services/pg_embeddings_manager.py
wizit_context_ingestor/utils/file_utils.py
wizit_context_ingestor/workflows/context_nodes.py
wizit_context_ingestor/workflows/context_state.py
wizit_context_ingestor/workflows/context_tools.py
wizit_context_ingestor/workflows/context_workflow.py
wizit_context_ingestor/workflows/transcription_nodes.py
wizit_context_ingestor/workflows/transcription_schemas.py
wizit_context_ingestor/workflows/transcription_state.py
wizit_context_ingestor/workflows/transcription_tools.py
wizit_context_ingestor-0.4.9.dist-info/WHEEL
wizit_context_ingestor-0.4.9.dist-info/METADATA
wizit_context_ingestor-0.4.9.dist-info/RECORD
