Metadata-Version: 2.3
Name: wizit-context-ingestor
Version: 0.4.9
Summary: Contextual Rag with Cloud Solutions
Requires-Dist: anthropic[vertex]>=0.66.0
Requires-Dist: boto3>=1.40.23
Requires-Dist: langchain-aws>=0.2.31
Requires-Dist: langchain-chroma>=0.2.6
Requires-Dist: langchain-experimental>=0.3.4
Requires-Dist: langchain-google-vertexai>=2.0.28
Requires-Dist: langchain-postgres>=0.0.16
Requires-Dist: langchain-redis>=0.2.3
Requires-Dist: langgraph>=0.6.8
Requires-Dist: pillow>=11.3.0
Requires-Dist: psycopg2-binary>=2.9.11
Requires-Dist: pymupdf>=1.26.4
Requires-Dist: sqlalchemy[asyncio]>=2.0.43
Requires-Python: >=3.12
